pytest_tdd/__init__.py
pytest_tdd/__main__.py
pytest_tdd/_build.py
pytest_tdd/api.py
pytest_tdd/cli.py
pytest_tdd-0.0.0.dist-info/METADATA
pytest_tdd-0.0.0.dist-info/WHEEL
pytest_tdd-0.0.0.dist-info/entry_points.txt
pytest_tdd-0.0.0.dist-info/licenses/LICENSE
pytest_tdd-0.0.0.dist-info/RECORD
