Metadata-Version: 2.1
Name: pytest-tdd
Version: 0.0.0
Summary: run pytest on a python module
Project-URL: Homepage, https://github.com/cav71/pytest-tdd
Project-URL: Documentation, https://github.com/cav71/pytest-tdd
Project-URL: Repository, https://github.com/cav71/pytest-tdd
Author-email: Antonio cavallo <a.cavallo@cavallinux.eu>
Maintainer-email: Antonio cavallo <a.cavallo@cavallinux.eu>
License: BSD 2-Clause License
License-File: LICENSE
Keywords: pre-commit
Classifier: Development Status :: 4 - Beta
Classifier: Programming Language :: Python
Requires-Python: >=3.8
